setup.cfg
setup.py
exportme/__init__.py
exportme.egg-info/PKG-INFO
exportme.egg-info/SOURCES.txt
exportme.egg-info/dependency_links.txt
exportme.egg-info/entry_points.txt
exportme.egg-info/requires.txt
exportme.egg-info/top_level.txt
exportme/core/__init__.py
exportme/core/admin.py
exportme/core/apps.py
exportme/core/models.py
exportme/core/views.py
exportme/core/management/__init__.py
exportme/core/management/commands/__init__.py
exportme/core/management/commands/list.py
exportme/core/migrations/0001_initial.py
exportme/core/migrations/__init__.py
exportme/exporters/__init__.py
exportme/exporters/currency.py
exportme/exporters/rescuetime.py
exportme/exporters/wanikani.py
exportme/standalone/__init__.py
exportme/standalone/manage.py
exportme/standalone/settings.py
exportme/standalone/urls.py
exportme/standalone/wsgi.py